aiopyrestful/__init__.py
aiopyrestful/exceptions.py
aiopyrestful/mediatypes.py
aiopyrestful/rest.py
aiopyrestful/types.py
aiopyrestful-1.4.1.dist-info/LICENSE
aiopyrestful-1.4.1.dist-info/METADATA
aiopyrestful-1.4.1.dist-info/WHEEL
aiopyrestful-1.4.1.dist-info/top_level.txt
aiopyrestful-1.4.1.dist-info/RECORD
