Metadata-Version: 2.1
Name: aiopyrestful
Version: 1.4.1
Summary: Restful framework with Tornado
Home-page: https://github.com/HarryHEi/aiopyrestful
Author: DarHarry
Author-email: harryx520@qq.com
License: UNKNOWN
Platform: UNKNOWN
Classifier: Programming Language :: Python :: 3
Requires-Dist: tornado
Requires-Dist: pyconvert
